senseppi/__init__.py
senseppi/__main__.py
senseppi/dataset.py
senseppi/esm2_model.py
senseppi/model.py
senseppi/network_utils.py
senseppi/utils.py
senseppi/commands/__init__.py
senseppi/commands/create_dataset.py
senseppi/commands/predict.py
senseppi/commands/predict_string.py
senseppi/commands/test.py
senseppi/commands/train.py
senseppi/default_model/fly_worm_human_chicken.ckpt
senseppi-0.7.5.dist-info/LICENSE
senseppi-0.7.5.dist-info/METADATA
senseppi-0.7.5.dist-info/WHEEL
senseppi-0.7.5.dist-info/entry_points.txt
senseppi-0.7.5.dist-info/top_level.txt
senseppi-0.7.5.dist-info/RECORD
