Metadata-Version: 2.1
Name: senseppi
Version: 0.7.5
Summary: SENSE-PPI: Sequence-based EvolutioNary ScalE Protein-Protein Interaction prediction
Home-page: 
Author: Konstantin Volzhenin
Author-email: Konstantin Volzhenin <konstantin_v_v@outlook.com>
License: MIT
Classifier: Programming Language :: Python :: 3
Classifier: Intended Audience :: Science/Research
Classifier: Operating System :: OS Independent
Requires-Python: >=3.9
License-File: LICENSE
Requires-Dist: numpy
Requires-Dist: pandas
Requires-Dist: wget
Requires-Dist: scipy
Requires-Dist: networkx
Requires-Dist: torch (>=1.12)
Requires-Dist: matplotlib
Requires-Dist: seaborn
Requires-Dist: tqdm
Requires-Dist: scikit-learn
Requires-Dist: pytorch-lightning (==1.9.0)
Requires-Dist: torchmetrics
Requires-Dist: biopython
Requires-Dist: fair-esm
Requires-Dist: pandarallel
